ckbit/__init__.py
ckbit/app_ea.py
ckbit/cstr.py
ckbit/pfr.py
ckbit/rxn_ord.py
ckbit-1.0.0.dist-info/LICENSE
ckbit-1.0.0.dist-info/METADATA
ckbit-1.0.0.dist-info/WHEEL
ckbit-1.0.0.dist-info/top_level.txt
ckbit-1.0.0.dist-info/zip-safe
ckbit-1.0.0.dist-info/RECORD
