Metadata-Version: 2.1
Name: ckbit
Version: 1.0.0
Summary: Kinetic Bayesian Inference
Home-page: https://github.com/VlachosGroup/ckbit
Author: Vlachos Research Group
Author-email: vlachos@udel.edu
License: UNKNOWN
Platform: UNKNOWN
Classifier: Programming Language :: Python
Classifier: License :: OSI Approved :: MIT License
Classifier: Operating System :: OS Independent
Classifier: Intended Audience :: Science/Research
Classifier: Topic :: Scientific/Engineering :: Chemistry
Requires-Python: >=3.7
Requires-Dist: numpy (>=1.16)
Requires-Dist: datetime
Requires-Dist: tabulate (>=0.8)
Requires-Dist: VUnits (>=0.0.3)
Requires-Dist: arviz (>=0.4)
Requires-Dist: pandas (>=0.25)
Requires-Dist: xlrd
Requires-Dist: openpyxl (>=3.0.0)
Requires-Dist: seaborn (>=0.9.0)
Requires-Dist: matplotlib (>=3.1)
